README.md
setup.cfg
setup.py
planting/__init__.py
planting/a.py
planting/main.py
planting/planting.py
planting/planting_api_v1.py
plantingtest.egg-info/PKG-INFO
plantingtest.egg-info/SOURCES.txt
plantingtest.egg-info/dependency_links.txt
plantingtest.egg-info/entry_points.txt
plantingtest.egg-info/requires.txt
plantingtest.egg-info/top_level.txt
plantingtest.egg-info/zip-safe
tests/__init__.py