Metadata-Version: 1.0
Name: plantingtest
Version: 1.0.0
Summary: a deploy tool for ficus
Home-page: https://github.com/yt-nebula/planting.git
Author: UNKNOWN
Author-email: UNKNOWN
License: UNKNOWN
Platform: UNKNOWN
